colt5/__init__.py
colt5-0.0.1.dev0.dist-info/METADATA
colt5-0.0.1.dev0.dist-info/WHEEL
colt5-0.0.1.dev0.dist-info/top_level.txt
colt5-0.0.1.dev0.dist-info/RECORD
