Metadata-Version: 2.1
Name: colt5
Version: 0.0.1.dev0
Summary: colt5 - Faster Long-Range Transformers with Conditional Computation
Author: Shadow Walker
License: UNKNOWN
Keywords: colt5
Platform: UNKNOWN
Classifier: Programming Language :: Python :: 3
Classifier: Programming Language :: Python :: 3.8
Classifier: Programming Language :: Python :: 3.9
Classifier: Programming Language :: Python :: 3.10
Requires-Dist: torch
